ArcDLNexus/__init__.py
ArcDLNexus/main.py
ArcDLNexus-0.1.5.dist-info/LICENSE
ArcDLNexus-0.1.5.dist-info/METADATA
ArcDLNexus-0.1.5.dist-info/WHEEL
ArcDLNexus-0.1.5.dist-info/top_level.txt
ArcDLNexus-0.1.5.dist-info/RECORD
