Metadata-Version: 2.1
Name: ArcDLNexus
Version: 0.1.5
Summary: ArcDLNexus: PythonからWayback Machineのアーカイブ（サイト）をダウンロードするモジュールです。
Home-page: https://github.com/harumaki4649/ArcDLNexus
Download-URL: https://github.com/harumaki4649/ArcDLNexus
Author: ArcDLNexus
Author-email: support@disnana.com
Maintainer: ArcDLNexus
Maintainer-email: support@disnana.com
License: BSD 3-Clause
Classifier: Intended Audience :: Science/Research
Classifier: License :: OSI Approved :: BSD License
Classifier: Programming Language :: Python :: 3
Classifier: Programming Language :: Python :: 3.6
Classifier: Programming Language :: Python :: 3.7
Classifier: Programming Language :: Python :: 3.8
Classifier: Programming Language :: Python :: 3.9
Classifier: Programming Language :: Python :: 3 :: Only
Classifier: Topic :: Scientific/Engineering
Classifier: Topic :: Scientific/Engineering :: Visualization
Classifier: Topic :: Scientific/Engineering :: Artificial Intelligence
Classifier: Topic :: Multimedia :: Graphics
Classifier: Framework :: Matplotlib
Requires-Python: >=3.9
License-File: LICENSE
Requires-Dist: requests ==2.32.2
Requires-Dist: beautifulsoup4 ==4.12.3
